versioned_dictionary/__init__.py
versioned_dictionary/utils.py
versioned_dictionary/versioned_dictionary.py
versioned_dictionary-0.1.1.dist-info/LICENSE
versioned_dictionary-0.1.1.dist-info/METADATA
versioned_dictionary-0.1.1.dist-info/WHEEL
versioned_dictionary-0.1.1.dist-info/top_level.txt
versioned_dictionary-0.1.1.dist-info/RECORD
