Metadata-Version: 2.1
Name: versioned-dictionary
Version: 0.1.1
Summary: A package that provides a class for makeing a full revision history of any dictionary
Home-page: https://andreacortis@bitbucket.org/andreacortis/versioned_dictionary.git
Author: Andrea Cortis
Author-email: andrea.cortis@gmail.com
License: MIT
Platform: UNKNOWN
Requires-Dist: json-tricks
Requires-Dist: python-jwt
Requires-Dist: pandas
